{
  "parent": "minecraft:recipes/root",
  "rewards": {
    "recipes": [
      "tirphycraft:poly_crystal_pyrodes_smelting"
    ]
  },
  "criteria": {
    "has_material": {
      "trigger": "minecraft:inventory_changed",
      "conditions": {
        "items": [
          {
            "item": "tirphycraft:crystal_purodes"
          }
        ]
      }
    },
    "has_the_recipe": {
      "trigger": "minecraft:recipe_unlocked",
      "conditions": {
        "recipe": "tirphycraft:poly_crystal_pyrodes_smelting"
      }
    }
  },
  "requirements": [
    [
      "has_material",
      "has_the_recipe"
    ]
  ]
}